{
    "@context": [
        "http://api.conceptnet.io/ld/conceptnet5.5/context.ld.json", 
        "http://api.conceptnet.io/ld/conceptnet5.5/pagination.ld.json"
    ], 
    "edges": [
        {
            "end": {
                "sense_label": "a", 
                "@id": "/c/en/bad/a", 
                "term": "/c/en/bad", 
                "language": "en", 
                "label": "bad"
            }, 
            "weight": 2.0, 
            "license": "cc:by/4.0", 
            "start": {
                "sense_label": "a", 
                "@id": "/c/en/evil/a", 
                "term": "/c/en/evil", 
                "language": "en", 
                "label": "evil"
            }, 
            "dataset": "/d/wordnet/3.1", 
            "sources": [
                {
                    "contributor": "/s/resource/wordnet/rdf/3.1", 
                    "@id": "/s/resource/wordnet/rdf/3.1"
                }
            ], 
            "rel": {
                "@id": "/r/SimilarTo", 
                "label": "SimilarTo"
            }, 
            "@id": "/a/[/r/SimilarTo/,/c/en/evil/a/,/c/en/bad/a/]", 
            "surfaceText": "[[evil]] is similar to [[bad]]"
        }, 
        {
            "end": {
                "sense_label": "a", 
                "@id": "/c/en/bad/a", 
                "term": "/c/en/bad", 
                "language": "en", 
                "label": "bad"
            }, 
            "weight": 2.0, 
            "license": "cc:by/4.0", 
            "start": {
                "sense_label": "a", 
                "@id": "/c/en/frightful/a", 
                "term": "/c/en/frightful", 
                "language": "en", 
                "label": "frightful"
            }, 
            "dataset": "/d/wordnet/3.1", 
            "sources": [
                {
                    "contributor": "/s/resource/wordnet/rdf/3.1", 
                    "@id": "/s/resource/wordnet/rdf/3.1"
                }
            ], 
            "rel": {
                "@id": "/r/SimilarTo", 
                "label": "SimilarTo"
            }, 
            "@id": "/a/[/r/SimilarTo/,/c/en/frightful/a/,/c/en/bad/a/]", 
            "surfaceText": "[[frightful]] is similar to [[bad]]"
        }, 
        {
            "end": {
                "sense_label": "a", 
                "@id": "/c/en/bad/a", 
                "term": "/c/en/bad", 
                "language": "en", 
                "label": "bad"
            }, 
            "weight": 2.0, 
            "license": "cc:by/4.0", 
            "start": {
                "sense_label": "a", 
                "@id": "/c/en/harmful/a", 
                "term": "/c/en/harmful", 
                "language": "en", 
                "label": "harmful"
            }, 
            "dataset": "/d/wordnet/3.1", 
            "sources": [
                {
                    "contributor": "/s/resource/wordnet/rdf/3.1", 
                    "@id": "/s/resource/wordnet/rdf/3.1"
                }
            ], 
            "rel": {
                "@id": "/r/SimilarTo", 
                "label": "SimilarTo"
            }, 
            "@id": "/a/[/r/SimilarTo/,/c/en/harmful/a/,/c/en/bad/a/]", 
            "surfaceText": "[[harmful]] is similar to [[bad]]"
        }, 
        {
            "end": {
                "sense_label": "a", 
                "@id": "/c/en/bad/a", 
                "term": "/c/en/bad", 
                "language": "en", 
                "label": "bad"
            }, 
            "weight": 2.0, 
            "license": "cc:by/4.0", 
            "start": {
                "sense_label": "a", 
                "@id": "/c/en/hopeless/a", 
                "term": "/c/en/hopeless", 
                "language": "en", 
                "label": "hopeless"
            }, 
            "dataset": "/d/wordnet/3.1", 
            "sources": [
                {
                    "contributor": "/s/resource/wordnet/rdf/3.1", 
                    "@id": "/s/resource/wordnet/rdf/3.1"
                }
            ], 
            "rel": {
                "@id": "/r/SimilarTo", 
                "label": "SimilarTo"
            }, 
            "@id": "/a/[/r/SimilarTo/,/c/en/hopeless/a/,/c/en/bad/a/]", 
            "surfaceText": "[[hopeless]] is similar to [[bad]]"
        }, 
        {
            "end": {
                "sense_label": "a", 
                "@id": "/c/en/bad/a", 
                "term": "/c/en/bad", 
                "language": "en", 
                "label": "bad"
            }, 
            "weight": 2.0, 
            "license": "cc:by/4.0", 
            "start": {
                "sense_label": "a", 
                "@id": "/c/en/horrid/a", 
                "term": "/c/en/horrid", 
                "language": "en", 
                "label": "horrid"
            }, 
            "dataset": "/d/wordnet/3.1", 
            "sources": [
                {
                    "contributor": "/s/resource/wordnet/rdf/3.1", 
                    "@id": "/s/resource/wordnet/rdf/3.1"
                }
            ], 
            "rel": {
                "@id": "/r/SimilarTo", 
                "label": "SimilarTo"
            }, 
            "@id": "/a/[/r/SimilarTo/,/c/en/horrid/a/,/c/en/bad/a/]", 
            "surfaceText": "[[horrid]] is similar to [[bad]]"
        }, 
        {
            "end": {
                "sense_label": "a", 
                "@id": "/c/en/bad/a", 
                "term": "/c/en/bad", 
                "language": "en", 
                "label": "bad"
            }, 
            "weight": 2.0, 
            "license": "cc:by/4.0", 
            "start": {
                "sense_label": "a", 
                "@id": "/c/en/ill/a", 
                "term": "/c/en/ill", 
                "language": "en", 
                "label": "ill"
            }, 
            "dataset": "/d/wordnet/3.1", 
            "sources": [
                {
                    "contributor": "/s/resource/wordnet/rdf/3.1", 
                    "@id": "/s/resource/wordnet/rdf/3.1"
                }
            ], 
            "rel": {
                "@id": "/r/SimilarTo", 
                "label": "SimilarTo"
            }, 
            "@id": "/a/[/r/SimilarTo/,/c/en/ill/a/,/c/en/bad/a/]", 
            "surfaceText": "[[ill]] is similar to [[bad]]"
        }, 
        {
            "end": {
                "sense_label": "a", 
                "@id": "/c/en/bad/a", 
                "term": "/c/en/bad", 
                "language": "en", 
                "label": "bad"
            }, 
            "weight": 2.0, 
            "license": "cc:by/4.0", 
            "start": {
                "sense_label": "a", 
                "@id": "/c/en/incompetent/a", 
                "term": "/c/en/incompetent", 
                "language": "en", 
                "label": "incompetent"
            }, 
            "dataset": "/d/wordnet/3.1", 
            "sources": [
                {
                    "contributor": "/s/resource/wordnet/rdf/3.1", 
                    "@id": "/s/resource/wordnet/rdf/3.1"
                }
            ], 
            "rel": {
                "@id": "/r/SimilarTo", 
                "label": "SimilarTo"
            }, 
            "@id": "/a/[/r/SimilarTo/,/c/en/incompetent/a/,/c/en/bad/a/]", 
            "surfaceText": "[[incompetent]] is similar to [[bad]]"
        }, 
        {
            "end": {
                "sense_label": "a", 
                "@id": "/c/en/bad/a", 
                "term": "/c/en/bad", 
                "language": "en", 
                "label": "bad"
            }, 
            "weight": 2.0, 
            "license": "cc:by/4.0", 
            "start": {
                "sense_label": "a", 
                "@id": "/c/en/inferior/a", 
                "term": "/c/en/inferior", 
                "language": "en", 
                "label": "inferior"
            }, 
            "dataset": "/d/wordnet/3.1", 
            "sources": [
                {
                    "contributor": "/s/resource/wordnet/rdf/3.1", 
                    "@id": "/s/resource/wordnet/rdf/3.1"
                }
            ], 
            "rel": {
                "@id": "/r/SimilarTo", 
                "label": "SimilarTo"
            }, 
            "@id": "/a/[/r/SimilarTo/,/c/en/inferior/a/,/c/en/bad/a/]", 
            "surfaceText": "[[inferior]] is similar to [[bad]]"
        }, 
        {
            "end": {
                "sense_label": "a", 
                "@id": "/c/en/bad/a", 
                "term": "/c/en/bad", 
                "language": "en", 
                "label": "bad"
            }, 
            "weight": 2.0, 
            "license": "cc:by/4.0", 
            "start": {
                "sense_label": "a", 
                "@id": "/c/en/intense/a", 
                "term": "/c/en/intense", 
                "language": "en", 
                "label": "intense"
            }, 
            "dataset": "/d/wordnet/3.1", 
            "sources": [
                {
                    "contributor": "/s/resource/wordnet/rdf/3.1", 
                    "@id": "/s/resource/wordnet/rdf/3.1"
                }
            ], 
            "rel": {
                "@id": "/r/SimilarTo", 
                "label": "SimilarTo"
            }, 
            "@id": "/a/[/r/SimilarTo/,/c/en/intense/a/,/c/en/bad/a/]", 
            "surfaceText": "[[intense]] is similar to [[bad]]"
        }, 
        {
            "end": {
                "sense_label": "a", 
                "@id": "/c/en/bad/a", 
                "term": "/c/en/bad", 
                "language": "en", 
                "label": "bad"
            }, 
            "weight": 2.0, 
            "license": "cc:by/4.0", 
            "start": {
                "sense_label": "a", 
                "@id": "/c/en/mediocre/a", 
                "term": "/c/en/mediocre", 
                "language": "en", 
                "label": "mediocre"
            }, 
            "dataset": "/d/wordnet/3.1", 
            "sources": [
                {
                    "contributor": "/s/resource/wordnet/rdf/3.1", 
                    "@id": "/s/resource/wordnet/rdf/3.1"
                }
            ], 
            "rel": {
                "@id": "/r/SimilarTo", 
                "label": "SimilarTo"
            }, 
            "@id": "/a/[/r/SimilarTo/,/c/en/mediocre/a/,/c/en/bad/a/]", 
            "surfaceText": "[[mediocre]] is similar to [[bad]]"
        }, 
        {
            "end": {
                "sense_label": "a", 
                "@id": "/c/en/bad/a", 
                "term": "/c/en/bad", 
                "language": "en", 
                "label": "bad"
            }, 
            "weight": 2.0, 
            "license": "cc:by/4.0", 
            "start": {
                "sense_label": "a", 
                "@id": "/c/en/naughty/a", 
                "term": "/c/en/naughty", 
                "language": "en", 
                "label": "naughty"
            }, 
            "dataset": "/d/wordnet/3.1", 
            "sources": [
                {
                    "contributor": "/s/resource/wordnet/rdf/3.1", 
                    "@id": "/s/resource/wordnet/rdf/3.1"
                }
            ], 
            "rel": {
                "@id": "/r/SimilarTo", 
                "label": "SimilarTo"
            }, 
            "@id": "/a/[/r/SimilarTo/,/c/en/naughty/a/,/c/en/bad/a/]", 
            "surfaceText": "[[naughty]] is similar to [[bad]]"
        }, 
        {
            "end": {
                "sense_label": "a", 
                "@id": "/c/en/bad/a", 
                "term": "/c/en/bad", 
                "language": "en", 
                "label": "bad"
            }, 
            "weight": 2.0, 
            "license": "cc:by/4.0", 
            "start": {
                "sense_label": "a", 
                "@id": "/c/en/negative/a", 
                "term": "/c/en/negative", 
                "language": "en", 
                "label": "negative"
            }, 
            "dataset": "/d/wordnet/3.1", 
            "sources": [
                {
                    "contributor": "/s/resource/wordnet/rdf/3.1", 
                    "@id": "/s/resource/wordnet/rdf/3.1"
                }
            ], 
            "rel": {
                "@id": "/r/SimilarTo", 
                "label": "SimilarTo"
            }, 
            "@id": "/a/[/r/SimilarTo/,/c/en/negative/a/,/c/en/bad/a/]", 
            "surfaceText": "[[negative]] is similar to [[bad]]"
        }, 
        {
            "end": {
                "sense_label": "a", 
                "@id": "/c/en/bad/a", 
                "term": "/c/en/bad", 
                "language": "en", 
                "label": "bad"
            }, 
            "weight": 2.0, 
            "license": "cc:by/4.0", 
            "start": {
                "sense_label": "a", 
                "@id": "/c/en/no_good/a", 
                "term": "/c/en/no_good", 
                "language": "en", 
                "label": "no-good"
            }, 
            "dataset": "/d/wordnet/3.1", 
            "sources": [
                {
                    "contributor": "/s/resource/wordnet/rdf/3.1", 
                    "@id": "/s/resource/wordnet/rdf/3.1"
                }
            ], 
            "rel": {
                "@id": "/r/SimilarTo", 
                "label": "SimilarTo"
            }, 
            "@id": "/a/[/r/SimilarTo/,/c/en/no_good/a/,/c/en/bad/a/]", 
            "surfaceText": "[[no-good]] is similar to [[bad]]"
        }, 
        {
            "end": {
                "sense_label": "a", 
                "@id": "/c/en/bad/a", 
                "term": "/c/en/bad", 
                "language": "en", 
                "label": "bad"
            }, 
            "weight": 2.0, 
            "license": "cc:by/4.0", 
            "start": {
                "sense_label": "a", 
                "@id": "/c/en/nonstandard/a", 
                "term": "/c/en/nonstandard", 
                "language": "en", 
                "label": "nonstandard"
            }, 
            "dataset": "/d/wordnet/3.1", 
            "sources": [
                {
                    "contributor": "/s/resource/wordnet/rdf/3.1", 
                    "@id": "/s/resource/wordnet/rdf/3.1"
                }
            ], 
            "rel": {
                "@id": "/r/SimilarTo", 
                "label": "SimilarTo"
            }, 
            "@id": "/a/[/r/SimilarTo/,/c/en/nonstandard/a/,/c/en/bad/a/]", 
            "surfaceText": "[[nonstandard]] is similar to [[bad]]"
        }, 
        {
            "end": {
                "sense_label": "a", 
                "@id": "/c/en/bad/a", 
                "term": "/c/en/bad", 
                "language": "en", 
                "label": "bad"
            }, 
            "weight": 2.0, 
            "license": "cc:by/4.0", 
            "start": {
                "sense_label": "a", 
                "@id": "/c/en/pretty/a", 
                "term": "/c/en/pretty", 
                "language": "en", 
                "label": "pretty"
            }, 
            "dataset": "/d/wordnet/3.1", 
            "sources": [
                {
                    "contributor": "/s/resource/wordnet/rdf/3.1", 
                    "@id": "/s/resource/wordnet/rdf/3.1"
                }
            ], 
            "rel": {
                "@id": "/r/SimilarTo", 
                "label": "SimilarTo"
            }, 
            "@id": "/a/[/r/SimilarTo/,/c/en/pretty/a/,/c/en/bad/a/]", 
            "surfaceText": "[[pretty]] is similar to [[bad]]"
        }, 
        {
            "end": {
                "sense_label": "a", 
                "@id": "/c/en/bad/a", 
                "term": "/c/en/bad", 
                "language": "en", 
                "label": "bad"
            }, 
            "weight": 2.0, 
            "license": "cc:by/4.0", 
            "start": {
                "sense_label": "a", 
                "@id": "/c/en/severe/a", 
                "term": "/c/en/severe", 
                "language": "en", 
                "label": "severe"
            }, 
            "dataset": "/d/wordnet/3.1", 
            "sources": [
                {
                    "contributor": "/s/resource/wordnet/rdf/3.1", 
                    "@id": "/s/resource/wordnet/rdf/3.1"
                }
            ], 
            "rel": {
                "@id": "/r/SimilarTo", 
                "label": "SimilarTo"
            }, 
            "@id": "/a/[/r/SimilarTo/,/c/en/severe/a/,/c/en/bad/a/]", 
            "surfaceText": "[[severe]] is similar to [[bad]]"
        }, 
        {
            "end": {
                "sense_label": "a", 
                "@id": "/c/en/bad/a", 
                "term": "/c/en/bad", 
                "language": "en", 
                "label": "bad"
            }, 
            "weight": 2.0, 
            "license": "cc:by/4.0", 
            "start": {
                "sense_label": "a", 
                "@id": "/c/en/stinking/a", 
                "term": "/c/en/stinking", 
                "language": "en", 
                "label": "stinking"
            }, 
            "dataset": "/d/wordnet/3.1", 
            "sources": [
                {
                    "contributor": "/s/resource/wordnet/rdf/3.1", 
                    "@id": "/s/resource/wordnet/rdf/3.1"
                }
            ], 
            "rel": {
                "@id": "/r/SimilarTo", 
                "label": "SimilarTo"
            }, 
            "@id": "/a/[/r/SimilarTo/,/c/en/stinking/a/,/c/en/bad/a/]", 
            "surfaceText": "[[stinking]] is similar to [[bad]]"
        }, 
        {
            "end": {
                "sense_label": "a", 
                "@id": "/c/en/bad/a", 
                "term": "/c/en/bad", 
                "language": "en", 
                "label": "bad"
            }, 
            "weight": 2.0, 
            "license": "cc:by/4.0", 
            "start": {
                "sense_label": "a", 
                "@id": "/c/en/swingeing/a", 
                "term": "/c/en/swingeing", 
                "language": "en", 
                "label": "swingeing"
            }, 
            "dataset": "/d/wordnet/3.1", 
            "sources": [
                {
                    "contributor": "/s/resource/wordnet/rdf/3.1", 
                    "@id": "/s/resource/wordnet/rdf/3.1"
                }
            ], 
            "rel": {
                "@id": "/r/SimilarTo", 
                "label": "SimilarTo"
            }, 
            "@id": "/a/[/r/SimilarTo/,/c/en/swingeing/a/,/c/en/bad/a/]", 
            "surfaceText": "[[swingeing]] is similar to [[bad]]"
        }, 
        {
            "end": {
                "sense_label": "a", 
                "@id": "/c/en/bad/a", 
                "term": "/c/en/bad", 
                "language": "en", 
                "label": "bad"
            }, 
            "weight": 2.0, 
            "license": "cc:by/4.0", 
            "start": {
                "sense_label": "a", 
                "@id": "/c/en/tough/a", 
                "term": "/c/en/tough", 
                "language": "en", 
                "label": "tough"
            }, 
            "dataset": "/d/wordnet/3.1", 
            "sources": [
                {
                    "contributor": "/s/resource/wordnet/rdf/3.1", 
                    "@id": "/s/resource/wordnet/rdf/3.1"
                }
            ], 
            "rel": {
                "@id": "/r/SimilarTo", 
                "label": "SimilarTo"
            }, 
            "@id": "/a/[/r/SimilarTo/,/c/en/tough/a/,/c/en/bad/a/]", 
            "surfaceText": "[[tough]] is similar to [[bad]]"
        }, 
        {
            "end": {
                "sense_label": "a", 
                "@id": "/c/en/bad/a", 
                "term": "/c/en/bad", 
                "language": "en", 
                "label": "bad"
            }, 
            "weight": 2.0, 
            "license": "cc:by/4.0", 
            "start": {
                "sense_label": "a", 
                "@id": "/c/en/uncool/a", 
                "term": "/c/en/uncool", 
                "language": "en", 
                "label": "uncool"
            }, 
            "dataset": "/d/wordnet/3.1", 
            "sources": [
                {
                    "contributor": "/s/resource/wordnet/rdf/3.1", 
                    "@id": "/s/resource/wordnet/rdf/3.1"
                }
            ], 
            "rel": {
                "@id": "/r/SimilarTo", 
                "label": "SimilarTo"
            }, 
            "@id": "/a/[/r/SimilarTo/,/c/en/uncool/a/,/c/en/bad/a/]", 
            "surfaceText": "[[uncool]] is similar to [[bad]]"
        }
    ], 
    "@id": "/c/en/bad", 
    "view": {
        "previousPage": "/c/en/bad?offset=60&limit=20", 
        "paginatedProperty": "edges", 
        "@id": "/c/en/bad?offset=80&limit=20", 
        "nextPage": "/c/en/bad?offset=100&limit=20", 
        "firstPage": "/c/en/bad?offset=0&limit=20"
    }
}