{
    "@context": [
        "http://api.conceptnet.io/ld/conceptnet5.5/context.ld.json", 
        "http://api.conceptnet.io/ld/conceptnet5.5/pagination.ld.json"
    ], 
    "edges": [
        {
            "end": {
                "sense_label": "n", 
                "@id": "/c/en/look/n", 
                "term": "/c/en/look", 
                "language": "en", 
                "label": "look"
            }, 
            "weight": 2.0, 
            "license": "cc:by/4.0", 
            "start": {
                "sense_label": "n", 
                "@id": "/c/ja/\u76ee\u898b/n", 
                "term": "/c/ja/\u76ee\u898b", 
                "language": "ja", 
                "label": "\u76ee\u898b"
            }, 
            "dataset": "/d/wordnet/3.1", 
            "sources": [
                {
                    "contributor": "/s/resource/wordnet/rdf/3.1", 
                    "@id": "/s/resource/wordnet/rdf/3.1"
                }
            ], 
            "rel": {
                "@id": "/r/Synonym", 
                "label": "Synonym"
            }, 
            "@id": "/a/[/r/Synonym/,/c/ja/\u76ee\u898b/n/,/c/en/look/n/]", 
            "surfaceText": "[[\u76ee\u898b]] is a translation of [[look]]"
        }, 
        {
            "end": {
                "term": "/c/en/look", 
                "@id": "/c/en/look", 
                "language": "en", 
                "label": "look"
            }, 
            "weight": 2.0, 
            "license": "cc:by-sa/4.0", 
            "start": {
                "sense_label": "n", 
                "@id": "/c/ja/\u76ee\u9762/n", 
                "term": "/c/ja/\u76ee\u9762", 
                "language": "ja", 
                "label": "\u76ee\u9762"
            }, 
            "dataset": "/d/jmdict", 
            "sources": [
                {
                    "contributor": "/s/resource/jmdict/1.07", 
                    "@id": "/s/resource/jmdict/1.07"
                }
            ], 
            "rel": {
                "@id": "/r/Synonym", 
                "label": "Synonym"
            }, 
            "@id": "/a/[/r/Synonym/,/c/ja/\u76ee\u9762/n/,/c/en/look/]", 
            "surfaceText": null
        }, 
        {
            "end": {
                "term": "/c/en/look", 
                "@id": "/c/en/look", 
                "language": "en", 
                "label": "look"
            }, 
            "weight": 2.0, 
            "license": "cc:by-sa/4.0", 
            "start": {
                "sense_label": "n", 
                "@id": "/c/ja/\u76ee\u9854/n", 
                "term": "/c/ja/\u76ee\u9854", 
                "language": "ja", 
                "label": "\u76ee\u9854"
            }, 
            "dataset": "/d/jmdict", 
            "sources": [
                {
                    "contributor": "/s/resource/jmdict/1.07", 
                    "@id": "/s/resource/jmdict/1.07"
                }
            ], 
            "rel": {
                "@id": "/r/Synonym", 
                "label": "Synonym"
            }, 
            "@id": "/a/[/r/Synonym/,/c/ja/\u76ee\u9854/n/,/c/en/look/]", 
            "surfaceText": null
        }, 
        {
            "end": {
                "sense_label": "n", 
                "@id": "/c/en/look/n", 
                "term": "/c/en/look", 
                "language": "en", 
                "label": "look"
            }, 
            "weight": 2.0, 
            "license": "cc:by/4.0", 
            "start": {
                "sense_label": "n", 
                "@id": "/c/ja/\u76ee\u9854/n", 
                "term": "/c/ja/\u76ee\u9854", 
                "language": "ja", 
                "label": "\u76ee\u9854"
            }, 
            "dataset": "/d/wordnet/3.1", 
            "sources": [
                {
                    "contributor": "/s/resource/wordnet/rdf/3.1", 
                    "@id": "/s/resource/wordnet/rdf/3.1"
                }
            ], 
            "rel": {
                "@id": "/r/Synonym", 
                "label": "Synonym"
            }, 
            "@id": "/a/[/r/Synonym/,/c/ja/\u76ee\u9854/n/,/c/en/look/n/]", 
            "surfaceText": "[[\u76ee\u9854]] is a translation of [[look]]"
        }, 
        {
            "end": {
                "term": "/c/en/look", 
                "@id": "/c/en/look", 
                "language": "en", 
                "label": "look"
            }, 
            "weight": 2.0, 
            "license": "cc:by-sa/4.0", 
            "start": {
                "sense_label": "n", 
                "@id": "/c/ja/\u76f8/n", 
                "term": "/c/ja/\u76f8", 
                "language": "ja", 
                "label": "\u76f8"
            }, 
            "dataset": "/d/jmdict", 
            "sources": [
                {
                    "contributor": "/s/resource/jmdict/1.07", 
                    "@id": "/s/resource/jmdict/1.07"
                }
            ], 
            "rel": {
                "@id": "/r/Synonym", 
                "label": "Synonym"
            }, 
            "@id": "/a/[/r/Synonym/,/c/ja/\u76f8/n/,/c/en/look/]", 
            "surfaceText": null
        }, 
        {
            "end": {
                "sense_label": "n", 
                "@id": "/c/en/look/n", 
                "term": "/c/en/look", 
                "language": "en", 
                "label": "look"
            }, 
            "weight": 2.0, 
            "license": "cc:by/4.0", 
            "start": {
                "sense_label": "n", 
                "@id": "/c/ja/\u76f8\u5f62/n", 
                "term": "/c/ja/\u76f8\u5f62", 
                "language": "ja", 
                "label": "\u76f8\u5f62"
            }, 
            "dataset": "/d/wordnet/3.1", 
            "sources": [
                {
                    "contributor": "/s/resource/wordnet/rdf/3.1", 
                    "@id": "/s/resource/wordnet/rdf/3.1"
                }
            ], 
            "rel": {
                "@id": "/r/Synonym", 
                "label": "Synonym"
            }, 
            "@id": "/a/[/r/Synonym/,/c/ja/\u76f8\u5f62/n/,/c/en/look/n/]", 
            "surfaceText": "[[\u76f8\u5f62]] is a translation of [[look]]"
        }, 
        {
            "end": {
                "sense_label": "n", 
                "@id": "/c/en/look/n", 
                "term": "/c/en/look", 
                "language": "en", 
                "label": "look"
            }, 
            "weight": 2.0, 
            "license": "cc:by/4.0", 
            "start": {
                "sense_label": "n", 
                "@id": "/c/ja/\u76f8\u8c8c/n", 
                "term": "/c/ja/\u76f8\u8c8c", 
                "language": "ja", 
                "label": "\u76f8\u8c8c"
            }, 
            "dataset": "/d/wordnet/3.1", 
            "sources": [
                {
                    "contributor": "/s/resource/wordnet/rdf/3.1", 
                    "@id": "/s/resource/wordnet/rdf/3.1"
                }
            ], 
            "rel": {
                "@id": "/r/Synonym", 
                "label": "Synonym"
            }, 
            "@id": "/a/[/r/Synonym/,/c/ja/\u76f8\u8c8c/n/,/c/en/look/n/]", 
            "surfaceText": "[[\u76f8\u8c8c]] is a translation of [[look]]"
        }, 
        {
            "end": {
                "term": "/c/en/look", 
                "@id": "/c/en/look", 
                "language": "en", 
                "label": "look"
            }, 
            "weight": 2.0, 
            "license": "cc:by-sa/4.0", 
            "start": {
                "sense_label": "v", 
                "@id": "/c/ja/\u770b\u3059/v", 
                "term": "/c/ja/\u770b\u3059", 
                "language": "ja", 
                "label": "\u770b\u3059"
            }, 
            "dataset": "/d/jmdict", 
            "sources": [
                {
                    "contributor": "/s/resource/jmdict/1.07", 
                    "@id": "/s/resource/jmdict/1.07"
                }
            ], 
            "rel": {
                "@id": "/r/Synonym", 
                "label": "Synonym"
            }, 
            "@id": "/a/[/r/Synonym/,/c/ja/\u770b\u3059/v/,/c/en/look/]", 
            "surfaceText": null
        }, 
        {
            "end": {
                "term": "/c/en/look", 
                "@id": "/c/en/look", 
                "language": "en", 
                "label": "look"
            }, 
            "weight": 2.0, 
            "license": "cc:by-sa/4.0", 
            "start": {
                "term": "/c/ja/\u770b\u677f", 
                "@id": "/c/ja/\u770b\u677f", 
                "language": "ja", 
                "label": "\u770b\u677f"
            }, 
            "dataset": "/d/jmdict", 
            "sources": [
                {
                    "contributor": "/s/resource/jmdict/1.07", 
                    "@id": "/s/resource/jmdict/1.07"
                }
            ], 
            "rel": {
                "@id": "/r/Synonym", 
                "label": "Synonym"
            }, 
            "@id": "/a/[/r/Synonym/,/c/ja/\u770b\u677f/,/c/en/look/]", 
            "surfaceText": null
        }, 
        {
            "end": {
                "sense_label": "v", 
                "@id": "/c/en/look/v", 
                "term": "/c/en/look", 
                "language": "en", 
                "label": "look"
            }, 
            "weight": 2.0, 
            "license": "cc:by/4.0", 
            "start": {
                "sense_label": "v", 
                "@id": "/c/ja/\u773a\u3081\u308b/v", 
                "term": "/c/ja/\u773a\u3081\u308b", 
                "language": "ja", 
                "label": "\u773a\u3081\u308b"
            }, 
            "dataset": "/d/wordnet/3.1", 
            "sources": [
                {
                    "contributor": "/s/resource/wordnet/rdf/3.1", 
                    "@id": "/s/resource/wordnet/rdf/3.1"
                }
            ], 
            "rel": {
                "@id": "/r/Synonym", 
                "label": "Synonym"
            }, 
            "@id": "/a/[/r/Synonym/,/c/ja/\u773a\u3081\u308b/v/,/c/en/look/v/]", 
            "surfaceText": "[[\u773a\u3081\u308b]] is a translation of [[look]]"
        }, 
        {
            "end": {
                "term": "/c/en/look", 
                "@id": "/c/en/look", 
                "language": "en", 
                "label": "look"
            }, 
            "weight": 2.0, 
            "license": "cc:by-sa/4.0", 
            "start": {
                "term": "/c/ja/\u773c", 
                "@id": "/c/ja/\u773c", 
                "language": "ja", 
                "label": "\u773c"
            }, 
            "dataset": "/d/jmdict", 
            "sources": [
                {
                    "contributor": "/s/resource/jmdict/1.07", 
                    "@id": "/s/resource/jmdict/1.07"
                }
            ], 
            "rel": {
                "@id": "/r/Synonym", 
                "label": "Synonym"
            }, 
            "@id": "/a/[/r/Synonym/,/c/ja/\u773c/,/c/en/look/]", 
            "surfaceText": null
        }, 
        {
            "end": {
                "term": "/c/en/look", 
                "@id": "/c/en/look", 
                "language": "en", 
                "label": "look"
            }, 
            "weight": 2.0, 
            "license": "cc:by-sa/4.0", 
            "start": {
                "sense_label": "n", 
                "@id": "/c/ja/\u773c\u3064\u304d/n", 
                "term": "/c/ja/\u773c\u3064\u304d", 
                "language": "ja", 
                "label": "\u773c\u3064\u304d"
            }, 
            "dataset": "/d/jmdict", 
            "sources": [
                {
                    "contributor": "/s/resource/jmdict/1.07", 
                    "@id": "/s/resource/jmdict/1.07"
                }
            ], 
            "rel": {
                "@id": "/r/Synonym", 
                "label": "Synonym"
            }, 
            "@id": "/a/[/r/Synonym/,/c/ja/\u773c\u3064\u304d/n/,/c/en/look/]", 
            "surfaceText": null
        }, 
        {
            "end": {
                "term": "/c/en/look", 
                "@id": "/c/en/look", 
                "language": "en", 
                "label": "look"
            }, 
            "weight": 2.0, 
            "license": "cc:by-sa/4.0", 
            "start": {
                "sense_label": "n", 
                "@id": "/c/ja/\u773c\u4ed8/n", 
                "term": "/c/ja/\u773c\u4ed8", 
                "language": "ja", 
                "label": "\u773c\u4ed8"
            }, 
            "dataset": "/d/jmdict", 
            "sources": [
                {
                    "contributor": "/s/resource/jmdict/1.07", 
                    "@id": "/s/resource/jmdict/1.07"
                }
            ], 
            "rel": {
                "@id": "/r/Synonym", 
                "label": "Synonym"
            }, 
            "@id": "/a/[/r/Synonym/,/c/ja/\u773c\u4ed8/n/,/c/en/look/]", 
            "surfaceText": null
        }, 
        {
            "end": {
                "term": "/c/en/look", 
                "@id": "/c/en/look", 
                "language": "en", 
                "label": "look"
            }, 
            "weight": 2.0, 
            "license": "cc:by-sa/4.0", 
            "start": {
                "sense_label": "n", 
                "@id": "/c/ja/\u773c\u4ed8\u304d/n", 
                "term": "/c/ja/\u773c\u4ed8\u304d", 
                "language": "ja", 
                "label": "\u773c\u4ed8\u304d"
            }, 
            "dataset": "/d/jmdict", 
            "sources": [
                {
                    "contributor": "/s/resource/jmdict/1.07", 
                    "@id": "/s/resource/jmdict/1.07"
                }
            ], 
            "rel": {
                "@id": "/r/Synonym", 
                "label": "Synonym"
            }, 
            "@id": "/a/[/r/Synonym/,/c/ja/\u773c\u4ed8\u304d/n/,/c/en/look/]", 
            "surfaceText": null
        }, 
        {
            "end": {
                "term": "/c/en/look", 
                "@id": "/c/en/look", 
                "language": "en", 
                "label": "look"
            }, 
            "weight": 2.0, 
            "license": "cc:by-sa/4.0", 
            "start": {
                "sense_label": "n", 
                "@id": "/c/ja/\u773c\u5dee\u3057/n", 
                "term": "/c/ja/\u773c\u5dee\u3057", 
                "language": "ja", 
                "label": "\u773c\u5dee\u3057"
            }, 
            "dataset": "/d/jmdict", 
            "sources": [
                {
                    "contributor": "/s/resource/jmdict/1.07", 
                    "@id": "/s/resource/jmdict/1.07"
                }
            ], 
            "rel": {
                "@id": "/r/Synonym", 
                "label": "Synonym"
            }, 
            "@id": "/a/[/r/Synonym/,/c/ja/\u773c\u5dee\u3057/n/,/c/en/look/]", 
            "surfaceText": null
        }, 
        {
            "end": {
                "term": "/c/en/look", 
                "@id": "/c/en/look", 
                "language": "en", 
                "label": "look"
            }, 
            "weight": 2.0, 
            "license": "cc:by-sa/4.0", 
            "start": {
                "sense_label": "n", 
                "@id": "/c/ja/\u773c\u6307/n", 
                "term": "/c/ja/\u773c\u6307", 
                "language": "ja", 
                "label": "\u773c\u6307"
            }, 
            "dataset": "/d/jmdict", 
            "sources": [
                {
                    "contributor": "/s/resource/jmdict/1.07", 
                    "@id": "/s/resource/jmdict/1.07"
                }
            ], 
            "rel": {
                "@id": "/r/Synonym", 
                "label": "Synonym"
            }, 
            "@id": "/a/[/r/Synonym/,/c/ja/\u773c\u6307/n/,/c/en/look/]", 
            "surfaceText": null
        }, 
        {
            "end": {
                "sense_label": "n", 
                "@id": "/c/en/look/n", 
                "term": "/c/en/look", 
                "language": "en", 
                "label": "look"
            }, 
            "weight": 2.0, 
            "license": "cc:by/4.0", 
            "start": {
                "sense_label": "n", 
                "@id": "/c/ja/\u7ca7\u3044/n", 
                "term": "/c/ja/\u7ca7\u3044", 
                "language": "ja", 
                "label": "\u7ca7\u3044"
            }, 
            "dataset": "/d/wordnet/3.1", 
            "sources": [
                {
                    "contributor": "/s/resource/wordnet/rdf/3.1", 
                    "@id": "/s/resource/wordnet/rdf/3.1"
                }
            ], 
            "rel": {
                "@id": "/r/Synonym", 
                "label": "Synonym"
            }, 
            "@id": "/a/[/r/Synonym/,/c/ja/\u7ca7\u3044/n/,/c/en/look/n/]", 
            "surfaceText": "[[\u7ca7\u3044]] is a translation of [[look]]"
        }, 
        {
            "end": {
                "term": "/c/en/look", 
                "@id": "/c/en/look", 
                "language": "en", 
                "label": "look"
            }, 
            "weight": 2.0, 
            "license": "cc:by-sa/4.0", 
            "start": {
                "term": "/c/ja/\u8272", 
                "@id": "/c/ja/\u8272", 
                "language": "ja", 
                "label": "\u8272"
            }, 
            "dataset": "/d/jmdict", 
            "sources": [
                {
                    "contributor": "/s/resource/jmdict/1.07", 
                    "@id": "/s/resource/jmdict/1.07"
                }
            ], 
            "rel": {
                "@id": "/r/Synonym", 
                "label": "Synonym"
            }, 
            "@id": "/a/[/r/Synonym/,/c/ja/\u8272/,/c/en/look/]", 
            "surfaceText": null
        }, 
        {
            "end": {
                "sense_label": "n", 
                "@id": "/c/en/look/n", 
                "term": "/c/en/look", 
                "language": "en", 
                "label": "look"
            }, 
            "weight": 2.0, 
            "license": "cc:by/4.0", 
            "start": {
                "sense_label": "n", 
                "@id": "/c/ja/\u8840\u76f8/n", 
                "term": "/c/ja/\u8840\u76f8", 
                "language": "ja", 
                "label": "\u8840\u76f8"
            }, 
            "dataset": "/d/wordnet/3.1", 
            "sources": [
                {
                    "contributor": "/s/resource/wordnet/rdf/3.1", 
                    "@id": "/s/resource/wordnet/rdf/3.1"
                }
            ], 
            "rel": {
                "@id": "/r/Synonym", 
                "label": "Synonym"
            }, 
            "@id": "/a/[/r/Synonym/,/c/ja/\u8840\u76f8/n/,/c/en/look/n/]", 
            "surfaceText": "[[\u8840\u76f8]] is a translation of [[look]]"
        }, 
        {
            "end": {
                "sense_label": "n", 
                "@id": "/c/en/look/n", 
                "term": "/c/en/look", 
                "language": "en", 
                "label": "look"
            }, 
            "weight": 2.0, 
            "license": "cc:by/4.0", 
            "start": {
                "sense_label": "n", 
                "@id": "/c/ja/\u8868\u60c5/n", 
                "term": "/c/ja/\u8868\u60c5", 
                "language": "ja", 
                "label": "\u8868\u60c5"
            }, 
            "dataset": "/d/wordnet/3.1", 
            "sources": [
                {
                    "contributor": "/s/resource/wordnet/rdf/3.1", 
                    "@id": "/s/resource/wordnet/rdf/3.1"
                }
            ], 
            "rel": {
                "@id": "/r/Synonym", 
                "label": "Synonym"
            }, 
            "@id": "/a/[/r/Synonym/,/c/ja/\u8868\u60c5/n/,/c/en/look/n/]", 
            "surfaceText": "[[\u8868\u60c5]] is a translation of [[look]]"
        }
    ], 
    "@id": "/c/en/look", 
    "view": {
        "previousPage": "/c/en/look?offset=180&limit=20", 
        "paginatedProperty": "edges", 
        "@id": "/c/en/look?offset=200&limit=20", 
        "nextPage": "/c/en/look?offset=220&limit=20", 
        "firstPage": "/c/en/look?offset=0&limit=20"
    }
}