{
    "@context": [
        "http://api.conceptnet.io/ld/conceptnet5.5/context.ld.json", 
        "http://api.conceptnet.io/ld/conceptnet5.5/pagination.ld.json"
    ], 
    "edges": [
        {
            "end": {
                "term": "/c/en/water", 
                "@id": "/c/en/water", 
                "language": "en", 
                "label": "water"
            }, 
            "weight": 2.0, 
            "license": "cc:by/4.0", 
            "start": {
                "term": "/c/en/having_shower", 
                "@id": "/c/en/having_shower", 
                "language": "en", 
                "label": "having a shower"
            }, 
            "dataset": "/d/conceptnet/4/en", 
            "sources": [
                {
                    "contributor": "/s/contributor/omcs/mj24", 
                    "@id": "/and/[/s/activity/omcs/omcs1_possibly_free_text/,/s/contributor/omcs/mj24/]", 
                    "activity": "/s/activity/omcs/omcs1_possibly_free_text"
                }, 
                {
                    "contributor": "/s/contributor/omcs/ali33", 
                    "@id": "/and/[/s/activity/omcs/vote/,/s/contributor/omcs/ali33/]", 
                    "activity": "/s/activity/omcs/vote"
                }
            ], 
            "rel": {
                "@id": "/r/HasPrerequisite", 
                "label": "HasPrerequisite"
            }, 
            "@id": "/a/[/r/HasPrerequisite/,/c/en/having_shower/,/c/en/water/]", 
            "surfaceText": "[[having a shower]] requires [[water]]"
        }, 
        {
            "end": {
                "term": "/c/en/water", 
                "@id": "/c/en/water", 
                "language": "en", 
                "label": "water"
            }, 
            "weight": 2.0, 
            "license": "cc:by/4.0", 
            "start": {
                "term": "/c/en/taking_bath", 
                "@id": "/c/en/taking_bath", 
                "language": "en", 
                "label": "taking a bath"
            }, 
            "dataset": "/d/conceptnet/4/en", 
            "sources": [
                {
                    "contributor": "/s/contributor/omcs/effendi", 
                    "@id": "/and/[/s/activity/omcs/omcs1_possibly_free_text/,/s/contributor/omcs/effendi/]", 
                    "activity": "/s/activity/omcs/omcs1_possibly_free_text"
                }, 
                {
                    "contributor": "/s/contributor/omcs/chrismoore", 
                    "@id": "/and/[/s/activity/omcs/vote/,/s/contributor/omcs/chrismoore/]", 
                    "activity": "/s/activity/omcs/vote"
                }
            ], 
            "rel": {
                "@id": "/r/HasPrerequisite", 
                "label": "HasPrerequisite"
            }, 
            "@id": "/a/[/r/HasPrerequisite/,/c/en/taking_bath/,/c/en/water/]", 
            "surfaceText": "[[taking a bath]] requires [[water]]"
        }, 
        {
            "end": {
                "term": "/c/en/water", 
                "@id": "/c/en/water", 
                "language": "en", 
                "label": "water"
            }, 
            "weight": 2.0, 
            "license": "cc:by/4.0", 
            "start": {
                "term": "/c/en/seventy_percent_of_earth's_surface", 
                "@id": "/c/en/seventy_percent_of_earth's_surface", 
                "language": "en", 
                "label": "Seventy percent of the earth's surface"
            }, 
            "dataset": "/d/conceptnet/4/en", 
            "sources": [
                {
                    "contributor": "/s/contributor/omcs/suncat", 
                    "@id": "/and/[/s/activity/omcs/omcs1_possibly_free_text/,/s/contributor/omcs/suncat/]", 
                    "activity": "/s/activity/omcs/omcs1_possibly_free_text"
                }, 
                {
                    "contributor": "/s/contributor/omcs/dexy", 
                    "@id": "/and/[/s/activity/omcs/vote/,/s/contributor/omcs/dexy/]", 
                    "activity": "/s/activity/omcs/vote"
                }
            ], 
            "rel": {
                "@id": "/r/HasProperty", 
                "label": "HasProperty"
            }, 
            "@id": "/a/[/r/HasProperty/,/c/en/seventy_percent_of_earth's_surface/,/c/en/water/]", 
            "surfaceText": "[[Seventy percent of the earth's surface]] is [[water]]"
        }, 
        {
            "end": {
                "term": "/c/en/dangerous", 
                "@id": "/c/en/dangerous", 
                "language": "en", 
                "label": "dangerous"
            }, 
            "weight": 2.0, 
            "license": "cc:by/4.0", 
            "start": {
                "term": "/c/en/water", 
                "@id": "/c/en/water", 
                "language": "en", 
                "label": "water"
            }, 
            "dataset": "/d/conceptnet/4/en", 
            "sources": [
                {
                    "contributor": "/s/contributor/omcs/amoffit", 
                    "@id": "/and/[/s/activity/omcs/omcs1_possibly_free_text/,/s/contributor/omcs/amoffit/]", 
                    "activity": "/s/activity/omcs/omcs1_possibly_free_text"
                }, 
                {
                    "contributor": "/s/contributor/omcs/browni", 
                    "@id": "/and/[/s/activity/omcs/vote/,/s/contributor/omcs/browni/]", 
                    "activity": "/s/activity/omcs/vote"
                }, 
                {
                    "contributor": "/s/contributor/omcs/markfarrar", 
                    "@id": "/and/[/s/activity/omcs/vote/,/s/contributor/omcs/markfarrar/]", 
                    "activity": "/s/activity/omcs/vote"
                }, 
                {
                    "contributor": "/s/contributor/omcs/sandos", 
                    "@id": "/and/[/s/activity/omcs/vote/,/s/contributor/omcs/sandos/]", 
                    "activity": "/s/activity/omcs/vote"
                }
            ], 
            "rel": {
                "@id": "/r/HasProperty", 
                "label": "HasProperty"
            }, 
            "@id": "/a/[/r/HasProperty/,/c/en/water/,/c/en/dangerous/]", 
            "surfaceText": "[[water]] can be [[dangerous]]"
        }, 
        {
            "end": {
                "term": "/c/en/essential_to_human_life", 
                "@id": "/c/en/essential_to_human_life", 
                "language": "en", 
                "label": "essential to human life"
            }, 
            "weight": 2.0, 
            "license": "cc:by/4.0", 
            "start": {
                "term": "/c/en/water", 
                "@id": "/c/en/water", 
                "language": "en", 
                "label": "Water"
            }, 
            "dataset": "/d/conceptnet/4/en", 
            "sources": [
                {
                    "contributor": "/s/contributor/omcs/effendi", 
                    "@id": "/and/[/s/activity/omcs/omcs1_possibly_free_text/,/s/contributor/omcs/effendi/]", 
                    "activity": "/s/activity/omcs/omcs1_possibly_free_text"
                }, 
                {
                    "contributor": "/s/contributor/omcs/evykay", 
                    "@id": "/and/[/s/activity/omcs/vote/,/s/contributor/omcs/evykay/]", 
                    "activity": "/s/activity/omcs/vote"
                }
            ], 
            "rel": {
                "@id": "/r/HasProperty", 
                "label": "HasProperty"
            }, 
            "@id": "/a/[/r/HasProperty/,/c/en/water/,/c/en/essential_to_human_life/]", 
            "surfaceText": "[[Water]] is [[essential to human life]]"
        }, 
        {
            "end": {
                "term": "/c/en/good_to_drink", 
                "@id": "/c/en/good_to_drink", 
                "language": "en", 
                "label": "good to drink"
            }, 
            "weight": 2.0, 
            "license": "cc:by/4.0", 
            "start": {
                "term": "/c/en/water", 
                "@id": "/c/en/water", 
                "language": "en", 
                "label": "water"
            }, 
            "dataset": "/d/conceptnet/4/en", 
            "sources": [
                {
                    "contributor": "/s/contributor/omcs/mashed", 
                    "@id": "/and/[/s/activity/omcs/omcs1_possibly_free_text/,/s/contributor/omcs/mashed/]", 
                    "activity": "/s/activity/omcs/omcs1_possibly_free_text"
                }, 
                {
                    "contributor": "/s/contributor/omcs/lzeke", 
                    "@id": "/and/[/s/activity/omcs/vote/,/s/contributor/omcs/lzeke/]", 
                    "activity": "/s/activity/omcs/vote"
                }
            ], 
            "rel": {
                "@id": "/r/HasProperty", 
                "label": "HasProperty"
            }, 
            "@id": "/a/[/r/HasProperty/,/c/en/water/,/c/en/good_to_drink/]", 
            "surfaceText": "[[water]] is [[good to drink]]"
        }, 
        {
            "end": {
                "term": "/c/en/much_more_stable_than_hydrogen_peroxide", 
                "@id": "/c/en/much_more_stable_than_hydrogen_peroxide", 
                "language": "en", 
                "label": "much more stable than hydrogen peroxide"
            }, 
            "weight": 2.0, 
            "license": "cc:by/4.0", 
            "start": {
                "term": "/c/en/water", 
                "@id": "/c/en/water", 
                "language": "en", 
                "label": "Water"
            }, 
            "dataset": "/d/conceptnet/4/en", 
            "sources": [
                {
                    "contributor": "/s/contributor/omcs/visionsofkaos", 
                    "@id": "/and/[/s/activity/omcs/omcs1_possibly_free_text/,/s/contributor/omcs/visionsofkaos/]", 
                    "activity": "/s/activity/omcs/omcs1_possibly_free_text"
                }, 
                {
                    "contributor": "/s/contributor/omcs/paulmcq2", 
                    "@id": "/and/[/s/activity/omcs/vote/,/s/contributor/omcs/paulmcq2/]", 
                    "activity": "/s/activity/omcs/vote"
                }
            ], 
            "rel": {
                "@id": "/r/HasProperty", 
                "label": "HasProperty"
            }, 
            "@id": "/a/[/r/HasProperty/,/c/en/water/,/c/en/much_more_stable_than_hydrogen_peroxide/]", 
            "surfaceText": "[[Water]] is [[much more stable than hydrogen peroxide]]"
        }, 
        {
            "end": {
                "sense_label": "n", 
                "@id": "/c/en/water/n", 
                "term": "/c/en/water", 
                "language": "en", 
                "label": "water"
            }, 
            "weight": 2.0, 
            "license": "cc:by/4.0", 
            "start": {
                "sense_label": "n", 
                "@id": "/c/en/bath_water/n", 
                "term": "/c/en/bath_water", 
                "language": "en", 
                "label": "bath water"
            }, 
            "dataset": "/d/wordnet/3.1", 
            "sources": [
                {
                    "contributor": "/s/resource/wordnet/rdf/3.1", 
                    "@id": "/s/resource/wordnet/rdf/3.1"
                }
            ], 
            "rel": {
                "@id": "/r/IsA", 
                "label": "IsA"
            }, 
            "@id": "/a/[/r/IsA/,/c/en/bath_water/n/,/c/en/water/n/]", 
            "surfaceText": "[[bath water]] is a type of [[water]]"
        }, 
        {
            "end": {
                "sense_label": "n", 
                "@id": "/c/en/water/n", 
                "term": "/c/en/water", 
                "language": "en", 
                "label": "water"
            }, 
            "weight": 2.0, 
            "license": "cc:by/4.0", 
            "start": {
                "sense_label": "n", 
                "@id": "/c/en/bilge/n", 
                "term": "/c/en/bilge", 
                "language": "en", 
                "label": "bilge"
            }, 
            "dataset": "/d/wordnet/3.1", 
            "sources": [
                {
                    "contributor": "/s/resource/wordnet/rdf/3.1", 
                    "@id": "/s/resource/wordnet/rdf/3.1"
                }
            ], 
            "rel": {
                "@id": "/r/IsA", 
                "label": "IsA"
            }, 
            "@id": "/a/[/r/IsA/,/c/en/bilge/n/,/c/en/water/n/]", 
            "surfaceText": "[[bilge]] is a type of [[water]]"
        }, 
        {
            "end": {
                "sense_label": "n", 
                "@id": "/c/en/water/n", 
                "term": "/c/en/water", 
                "language": "en", 
                "label": "water"
            }, 
            "weight": 2.0, 
            "license": "cc:by/4.0", 
            "start": {
                "sense_label": "n", 
                "@id": "/c/en/branch_water/n", 
                "term": "/c/en/branch_water", 
                "language": "en", 
                "label": "branch water"
            }, 
            "dataset": "/d/wordnet/3.1", 
            "sources": [
                {
                    "contributor": "/s/resource/wordnet/rdf/3.1", 
                    "@id": "/s/resource/wordnet/rdf/3.1"
                }
            ], 
            "rel": {
                "@id": "/r/IsA", 
                "label": "IsA"
            }, 
            "@id": "/a/[/r/IsA/,/c/en/branch_water/n/,/c/en/water/n/]", 
            "surfaceText": "[[branch water]] is a type of [[water]]"
        }, 
        {
            "end": {
                "sense_label": "n", 
                "@id": "/c/en/water/n", 
                "term": "/c/en/water", 
                "language": "en", 
                "label": "water"
            }, 
            "weight": 2.0, 
            "license": "cc:by/4.0", 
            "start": {
                "sense_label": "n", 
                "@id": "/c/en/dishwater/n", 
                "term": "/c/en/dishwater", 
                "language": "en", 
                "label": "dishwater"
            }, 
            "dataset": "/d/wordnet/3.1", 
            "sources": [
                {
                    "contributor": "/s/resource/wordnet/rdf/3.1", 
                    "@id": "/s/resource/wordnet/rdf/3.1"
                }
            ], 
            "rel": {
                "@id": "/r/IsA", 
                "label": "IsA"
            }, 
            "@id": "/a/[/r/IsA/,/c/en/dishwater/n/,/c/en/water/n/]", 
            "surfaceText": "[[dishwater]] is a type of [[water]]"
        }, 
        {
            "end": {
                "sense_label": "n", 
                "@id": "/c/en/water/n", 
                "term": "/c/en/water", 
                "language": "en", 
                "label": "water"
            }, 
            "weight": 2.0, 
            "license": "cc:by/4.0", 
            "start": {
                "sense_label": "n", 
                "@id": "/c/en/distilled_water/n", 
                "term": "/c/en/distilled_water", 
                "language": "en", 
                "label": "distilled water"
            }, 
            "dataset": "/d/wordnet/3.1", 
            "sources": [
                {
                    "contributor": "/s/resource/wordnet/rdf/3.1", 
                    "@id": "/s/resource/wordnet/rdf/3.1"
                }
            ], 
            "rel": {
                "@id": "/r/IsA", 
                "label": "IsA"
            }, 
            "@id": "/a/[/r/IsA/,/c/en/distilled_water/n/,/c/en/water/n/]", 
            "surfaceText": "[[distilled water]] is a type of [[water]]"
        }, 
        {
            "end": {
                "sense_label": "n", 
                "@id": "/c/en/water/n", 
                "term": "/c/en/water", 
                "language": "en", 
                "label": "water"
            }, 
            "weight": 2.0, 
            "license": "cc:by/4.0", 
            "start": {
                "sense_label": "n", 
                "@id": "/c/en/drinking_water/n", 
                "term": "/c/en/drinking_water", 
                "language": "en", 
                "label": "drinking water"
            }, 
            "dataset": "/d/wordnet/3.1", 
            "sources": [
                {
                    "contributor": "/s/resource/wordnet/rdf/3.1", 
                    "@id": "/s/resource/wordnet/rdf/3.1"
                }
            ], 
            "rel": {
                "@id": "/r/IsA", 
                "label": "IsA"
            }, 
            "@id": "/a/[/r/IsA/,/c/en/drinking_water/n/,/c/en/water/n/]", 
            "surfaceText": "[[drinking water]] is a type of [[water]]"
        }, 
        {
            "end": {
                "sense_label": "v", 
                "@id": "/c/en/water/v", 
                "term": "/c/en/water", 
                "language": "en", 
                "label": "water"
            }, 
            "weight": 2.0, 
            "license": "cc:by/4.0", 
            "start": {
                "sense_label": "v", 
                "@id": "/c/en/flush/v", 
                "term": "/c/en/flush", 
                "language": "en", 
                "label": "flush"
            }, 
            "dataset": "/d/wordnet/3.1", 
            "sources": [
                {
                    "contributor": "/s/resource/wordnet/rdf/3.1", 
                    "@id": "/s/resource/wordnet/rdf/3.1"
                }
            ], 
            "rel": {
                "@id": "/r/IsA", 
                "label": "IsA"
            }, 
            "@id": "/a/[/r/IsA/,/c/en/flush/v/,/c/en/water/v/]", 
            "surfaceText": "[[flush]] is a type of [[water]]"
        }, 
        {
            "end": {
                "sense_label": "n", 
                "@id": "/c/en/water/n", 
                "term": "/c/en/water", 
                "language": "en", 
                "label": "water"
            }, 
            "weight": 2.0, 
            "license": "cc:by/4.0", 
            "start": {
                "sense_label": "n", 
                "@id": "/c/en/ground_water/n", 
                "term": "/c/en/ground_water", 
                "language": "en", 
                "label": "ground water"
            }, 
            "dataset": "/d/wordnet/3.1", 
            "sources": [
                {
                    "contributor": "/s/resource/wordnet/rdf/3.1", 
                    "@id": "/s/resource/wordnet/rdf/3.1"
                }
            ], 
            "rel": {
                "@id": "/r/IsA", 
                "label": "IsA"
            }, 
            "@id": "/a/[/r/IsA/,/c/en/ground_water/n/,/c/en/water/n/]", 
            "surfaceText": "[[ground water]] is a type of [[water]]"
        }, 
        {
            "end": {
                "sense_label": "n", 
                "@id": "/c/en/water/n", 
                "term": "/c/en/water", 
                "language": "en", 
                "label": "water"
            }, 
            "weight": 2.0, 
            "license": "cc:by/4.0", 
            "start": {
                "sense_label": "n", 
                "@id": "/c/en/holy_water/n", 
                "term": "/c/en/holy_water", 
                "language": "en", 
                "label": "holy water"
            }, 
            "dataset": "/d/wordnet/3.1", 
            "sources": [
                {
                    "contributor": "/s/resource/wordnet/rdf/3.1", 
                    "@id": "/s/resource/wordnet/rdf/3.1"
                }
            ], 
            "rel": {
                "@id": "/r/IsA", 
                "label": "IsA"
            }, 
            "@id": "/a/[/r/IsA/,/c/en/holy_water/n/,/c/en/water/n/]", 
            "surfaceText": "[[holy water]] is a type of [[water]]"
        }, 
        {
            "end": {
                "sense_label": "v", 
                "@id": "/c/en/water/v", 
                "term": "/c/en/water", 
                "language": "en", 
                "label": "water"
            }, 
            "weight": 2.0, 
            "license": "cc:by/4.0", 
            "start": {
                "sense_label": "v", 
                "@id": "/c/en/hose/v", 
                "term": "/c/en/hose", 
                "language": "en", 
                "label": "hose"
            }, 
            "dataset": "/d/wordnet/3.1", 
            "sources": [
                {
                    "contributor": "/s/resource/wordnet/rdf/3.1", 
                    "@id": "/s/resource/wordnet/rdf/3.1"
                }
            ], 
            "rel": {
                "@id": "/r/IsA", 
                "label": "IsA"
            }, 
            "@id": "/a/[/r/IsA/,/c/en/hose/v/,/c/en/water/v/]", 
            "surfaceText": "[[hose]] is a type of [[water]]"
        }, 
        {
            "end": {
                "sense_label": "v", 
                "@id": "/c/en/water/v", 
                "term": "/c/en/water", 
                "language": "en", 
                "label": "water"
            }, 
            "weight": 2.0, 
            "license": "cc:by/4.0", 
            "start": {
                "sense_label": "v", 
                "@id": "/c/en/hush/v", 
                "term": "/c/en/hush", 
                "language": "en", 
                "label": "hush"
            }, 
            "dataset": "/d/wordnet/3.1", 
            "sources": [
                {
                    "contributor": "/s/resource/wordnet/rdf/3.1", 
                    "@id": "/s/resource/wordnet/rdf/3.1"
                }
            ], 
            "rel": {
                "@id": "/r/IsA", 
                "label": "IsA"
            }, 
            "@id": "/a/[/r/IsA/,/c/en/hush/v/,/c/en/water/v/]", 
            "surfaceText": "[[hush]] is a type of [[water]]"
        }, 
        {
            "end": {
                "sense_label": "n", 
                "@id": "/c/en/water/n", 
                "term": "/c/en/water", 
                "language": "en", 
                "label": "water"
            }, 
            "weight": 2.0, 
            "license": "cc:by/4.0", 
            "start": {
                "sense_label": "n", 
                "@id": "/c/en/limewater/n", 
                "term": "/c/en/limewater", 
                "language": "en", 
                "label": "limewater"
            }, 
            "dataset": "/d/wordnet/3.1", 
            "sources": [
                {
                    "contributor": "/s/resource/wordnet/rdf/3.1", 
                    "@id": "/s/resource/wordnet/rdf/3.1"
                }
            ], 
            "rel": {
                "@id": "/r/IsA", 
                "label": "IsA"
            }, 
            "@id": "/a/[/r/IsA/,/c/en/limewater/n/,/c/en/water/n/]", 
            "surfaceText": "[[limewater]] is a type of [[water]]"
        }, 
        {
            "end": {
                "sense_label": "n", 
                "@id": "/c/en/water/n", 
                "term": "/c/en/water", 
                "language": "en", 
                "label": "water"
            }, 
            "weight": 2.0, 
            "license": "cc:by/4.0", 
            "start": {
                "sense_label": "n", 
                "@id": "/c/en/meltwater/n", 
                "term": "/c/en/meltwater", 
                "language": "en", 
                "label": "meltwater"
            }, 
            "dataset": "/d/wordnet/3.1", 
            "sources": [
                {
                    "contributor": "/s/resource/wordnet/rdf/3.1", 
                    "@id": "/s/resource/wordnet/rdf/3.1"
                }
            ], 
            "rel": {
                "@id": "/r/IsA", 
                "label": "IsA"
            }, 
            "@id": "/a/[/r/IsA/,/c/en/meltwater/n/,/c/en/water/n/]", 
            "surfaceText": "[[meltwater]] is a type of [[water]]"
        }
    ], 
    "@id": "/c/en/water", 
    "view": {
        "previousPage": "/c/en/water?offset=160&limit=20", 
        "paginatedProperty": "edges", 
        "@id": "/c/en/water?offset=180&limit=20", 
        "nextPage": "/c/en/water?offset=200&limit=20", 
        "firstPage": "/c/en/water?offset=0&limit=20"
    }
}