{
    "@context": [
        "http://api.conceptnet.io/ld/conceptnet5.5/context.ld.json", 
        "http://api.conceptnet.io/ld/conceptnet5.5/pagination.ld.json"
    ], 
    "edges": [
        {
            "end": {
                "term": "http://wordnet-rdf.princeton.edu/wn31/step+up+to+the+plate-p#Component-2", 
                "@id": "http://wordnet-rdf.princeton.edu/wn31/step+up+to+the+plate-p#Component-2", 
                "site": "wordnet-rdf.princeton.edu", 
                "label": "step+up+to+the+plate-p#Component-2"
            }, 
            "weight": 1.0, 
            "license": "cc:by-sa/4.0", 
            "start": {
                "term": "/c/en/up", 
                "@id": "/c/en/up", 
                "language": "en", 
                "label": "up"
            }, 
            "dataset": "/d/wordnet/3.1", 
            "sources": [
                {
                    "contributor": "/s/resource/wordnet/rdf/3.1", 
                    "@id": "/s/resource/wordnet/rdf/3.1"
                }
            ], 
            "rel": {
                "@id": "/r/ExternalURL", 
                "label": "ExternalURL"
            }, 
            "@id": "/a/[/r/ExternalURL/,/c/en/up/,/http://wordnet-rdf.princeton.edu/wn31/step+up+to+the+plate-p#Component-2/]", 
            "surfaceText": null
        }, 
        {
            "end": {
                "term": "http://wordnet-rdf.princeton.edu/wn31/take+up+the+torch-p#Component-2", 
                "@id": "http://wordnet-rdf.princeton.edu/wn31/take+up+the+torch-p#Component-2", 
                "site": "wordnet-rdf.princeton.edu", 
                "label": "take+up+the+torch-p#Component-2"
            }, 
            "weight": 1.0, 
            "license": "cc:by-sa/4.0", 
            "start": {
                "term": "/c/en/up", 
                "@id": "/c/en/up", 
                "language": "en", 
                "label": "up"
            }, 
            "dataset": "/d/wordnet/3.1", 
            "sources": [
                {
                    "contributor": "/s/resource/wordnet/rdf/3.1", 
                    "@id": "/s/resource/wordnet/rdf/3.1"
                }
            ], 
            "rel": {
                "@id": "/r/ExternalURL", 
                "label": "ExternalURL"
            }, 
            "@id": "/a/[/r/ExternalURL/,/c/en/up/,/http://wordnet-rdf.princeton.edu/wn31/take+up+the+torch-p#Component-2/]", 
            "surfaceText": null
        }, 
        {
            "end": {
                "term": "http://wordnet-rdf.princeton.edu/wn31/turn+your+nose+up-p#Component-4", 
                "@id": "http://wordnet-rdf.princeton.edu/wn31/turn+your+nose+up-p#Component-4", 
                "site": "wordnet-rdf.princeton.edu", 
                "label": "turn+your+nose+up-p#Component-4"
            }, 
            "weight": 1.0, 
            "license": "cc:by-sa/4.0", 
            "start": {
                "term": "/c/en/up", 
                "@id": "/c/en/up", 
                "language": "en", 
                "label": "up"
            }, 
            "dataset": "/d/wordnet/3.1", 
            "sources": [
                {
                    "contributor": "/s/resource/wordnet/rdf/3.1", 
                    "@id": "/s/resource/wordnet/rdf/3.1"
                }
            ], 
            "rel": {
                "@id": "/r/ExternalURL", 
                "label": "ExternalURL"
            }, 
            "@id": "/a/[/r/ExternalURL/,/c/en/up/,/http://wordnet-rdf.princeton.edu/wn31/turn+your+nose+up-p#Component-4/]", 
            "surfaceText": null
        }, 
        {
            "end": {
                "term": "http://wordnet-rdf.princeton.edu/wn31/up+the+ante-p#Component-1", 
                "@id": "http://wordnet-rdf.princeton.edu/wn31/up+the+ante-p#Component-1", 
                "site": "wordnet-rdf.princeton.edu", 
                "label": "up+the+ante-p#Component-1"
            }, 
            "weight": 1.0, 
            "license": "cc:by-sa/4.0", 
            "start": {
                "term": "/c/en/up", 
                "@id": "/c/en/up", 
                "language": "en", 
                "label": "up"
            }, 
            "dataset": "/d/wordnet/3.1", 
            "sources": [
                {
                    "contributor": "/s/resource/wordnet/rdf/3.1", 
                    "@id": "/s/resource/wordnet/rdf/3.1"
                }
            ], 
            "rel": {
                "@id": "/r/ExternalURL", 
                "label": "ExternalURL"
            }, 
            "@id": "/a/[/r/ExternalURL/,/c/en/up/,/http://wordnet-rdf.princeton.edu/wn31/up+the+ante-p#Component-1/]", 
            "surfaceText": null
        }, 
        {
            "end": {
                "term": "http://sw.opencyc.org/2012/05/10/concept/en/Up_PortAdministrativeStatus", 
                "@id": "http://sw.opencyc.org/2012/05/10/concept/en/Up_PortAdministrativeStatus", 
                "site": "sw.opencyc.org", 
                "label": "Up PortAdministrativeStatus"
            }, 
            "weight": 1.0, 
            "license": "cc:by/4.0", 
            "start": {
                "sense_label": "n", 
                "@id": "/c/en/up/n", 
                "term": "/c/en/up", 
                "language": "en", 
                "label": "up"
            }, 
            "dataset": "/d/opencyc", 
            "sources": [
                {
                    "contributor": "/s/resource/opencyc/2012", 
                    "@id": "/s/resource/opencyc/2012"
                }
            ], 
            "rel": {
                "@id": "/r/ExternalURL", 
                "label": "ExternalURL"
            }, 
            "@id": "/a/[/r/ExternalURL/,/c/en/up/n/,/http://sw.opencyc.org/2012/05/10/concept/en/Up_PortAdministrativeStatus/]", 
            "surfaceText": null
        }, 
        {
            "end": {
                "term": "http://wordnet-rdf.princeton.edu/wn31/400097310-r", 
                "@id": "http://wordnet-rdf.princeton.edu/wn31/400097310-r", 
                "site": "wordnet-rdf.princeton.edu", 
                "label": "400097310-r"
            }, 
            "weight": 1.0, 
            "license": "cc:by-sa/4.0", 
            "start": {
                "sense_label": "r", 
                "@id": "/c/en/up/r", 
                "term": "/c/en/up", 
                "language": "en", 
                "label": "up"
            }, 
            "dataset": "/d/wordnet/3.1", 
            "sources": [
                {
                    "contributor": "/s/resource/wordnet/rdf/3.1", 
                    "@id": "/s/resource/wordnet/rdf/3.1"
                }
            ], 
            "rel": {
                "@id": "/r/ExternalURL", 
                "label": "ExternalURL"
            }, 
            "@id": "/a/[/r/ExternalURL/,/c/en/up/r/,/http://wordnet-rdf.princeton.edu/wn31/400097310-r/]", 
            "surfaceText": null
        }, 
        {
            "end": {
                "term": "http://wordnet-rdf.princeton.edu/wn31/400097471-r", 
                "@id": "http://wordnet-rdf.princeton.edu/wn31/400097471-r", 
                "site": "wordnet-rdf.princeton.edu", 
                "label": "400097471-r"
            }, 
            "weight": 1.0, 
            "license": "cc:by-sa/4.0", 
            "start": {
                "sense_label": "r", 
                "@id": "/c/en/up/r", 
                "term": "/c/en/up", 
                "language": "en", 
                "label": "up"
            }, 
            "dataset": "/d/wordnet/3.1", 
            "sources": [
                {
                    "contributor": "/s/resource/wordnet/rdf/3.1", 
                    "@id": "/s/resource/wordnet/rdf/3.1"
                }
            ], 
            "rel": {
                "@id": "/r/ExternalURL", 
                "label": "ExternalURL"
            }, 
            "@id": "/a/[/r/ExternalURL/,/c/en/up/r/,/http://wordnet-rdf.princeton.edu/wn31/400097471-r/]", 
            "surfaceText": null
        }, 
        {
            "end": {
                "term": "http://wordnet-rdf.princeton.edu/wn31/400097561-r", 
                "@id": "http://wordnet-rdf.princeton.edu/wn31/400097561-r", 
                "site": "wordnet-rdf.princeton.edu", 
                "label": "400097561-r"
            }, 
            "weight": 1.0, 
            "license": "cc:by-sa/4.0", 
            "start": {
                "sense_label": "r", 
                "@id": "/c/en/up/r", 
                "term": "/c/en/up", 
                "language": "en", 
                "label": "up"
            }, 
            "dataset": "/d/wordnet/3.1", 
            "sources": [
                {
                    "contributor": "/s/resource/wordnet/rdf/3.1", 
                    "@id": "/s/resource/wordnet/rdf/3.1"
                }
            ], 
            "rel": {
                "@id": "/r/ExternalURL", 
                "label": "ExternalURL"
            }, 
            "@id": "/a/[/r/ExternalURL/,/c/en/up/r/,/http://wordnet-rdf.princeton.edu/wn31/400097561-r/]", 
            "surfaceText": null
        }, 
        {
            "end": {
                "term": "http://wordnet-rdf.princeton.edu/wn31/200154774-v", 
                "@id": "http://wordnet-rdf.princeton.edu/wn31/200154774-v", 
                "site": "wordnet-rdf.princeton.edu", 
                "label": "200154774-v"
            }, 
            "weight": 1.0, 
            "license": "cc:by-sa/4.0", 
            "start": {
                "sense_label": "v", 
                "@id": "/c/en/up/v", 
                "term": "/c/en/up", 
                "language": "en", 
                "label": "up"
            }, 
            "dataset": "/d/wordnet/3.1", 
            "sources": [
                {
                    "contributor": "/s/resource/wordnet/rdf/3.1", 
                    "@id": "/s/resource/wordnet/rdf/3.1"
                }
            ], 
            "rel": {
                "@id": "/r/ExternalURL", 
                "label": "ExternalURL"
            }, 
            "@id": "/a/[/r/ExternalURL/,/c/en/up/v/,/http://wordnet-rdf.princeton.edu/wn31/200154774-v/]", 
            "surfaceText": null
        }, 
        {
            "end": {
                "term": "/c/en/up", 
                "@id": "/c/en/up", 
                "language": "en", 
                "label": "up"
            }, 
            "weight": 1.0, 
            "license": "cc:by-sa/4.0", 
            "start": {
                "sense_label": "n", 
                "@id": "/c/en/u.p/n", 
                "term": "/c/en/u.p", 
                "language": "en", 
                "label": "u.p"
            }, 
            "dataset": "/d/wiktionary/en", 
            "sources": [
                {
                    "contributor": "/s/resource/wiktionary/en", 
                    "process": "/s/process/wikiparsec/1", 
                    "@id": "/and/[/s/process/wikiparsec/1/,/s/resource/wiktionary/en/]"
                }
            ], 
            "rel": {
                "@id": "/r/FormOf", 
                "label": "FormOf"
            }, 
            "@id": "/a/[/r/FormOf/,/c/en/u.p/n/,/c/en/up/]", 
            "surfaceText": null
        }, 
        {
            "end": {
                "term": "/c/en/up", 
                "@id": "/c/en/up", 
                "language": "en", 
                "label": "up"
            }, 
            "weight": 1.0, 
            "license": "cc:by-sa/4.0", 
            "start": {
                "sense_label": "v", 
                "@id": "/c/en/upped/v", 
                "term": "/c/en/upped", 
                "language": "en", 
                "label": "upped"
            }, 
            "dataset": "/d/wiktionary/en", 
            "sources": [
                {
                    "contributor": "/s/resource/wiktionary/en", 
                    "process": "/s/process/wikiparsec/1", 
                    "@id": "/and/[/s/process/wikiparsec/1/,/s/resource/wiktionary/en/]"
                }
            ], 
            "rel": {
                "@id": "/r/FormOf", 
                "label": "FormOf"
            }, 
            "@id": "/a/[/r/FormOf/,/c/en/upped/v/,/c/en/up/]", 
            "surfaceText": null
        }, 
        {
            "end": {
                "term": "/c/en/up", 
                "@id": "/c/en/up", 
                "language": "en", 
                "label": "up"
            }, 
            "weight": 1.0, 
            "license": "cc:by-sa/4.0", 
            "start": {
                "sense_label": "v", 
                "@id": "/c/en/upping/v", 
                "term": "/c/en/upping", 
                "language": "en", 
                "label": "upping"
            }, 
            "dataset": "/d/wiktionary/en", 
            "sources": [
                {
                    "contributor": "/s/resource/wiktionary/en", 
                    "process": "/s/process/wikiparsec/1", 
                    "@id": "/and/[/s/process/wikiparsec/1/,/s/resource/wiktionary/en/]"
                }
            ], 
            "rel": {
                "@id": "/r/FormOf", 
                "label": "FormOf"
            }, 
            "@id": "/a/[/r/FormOf/,/c/en/upping/v/,/c/en/up/]", 
            "surfaceText": null
        }, 
        {
            "end": {
                "term": "/c/en/up", 
                "@id": "/c/en/up", 
                "language": "en", 
                "label": "up"
            }, 
            "weight": 1.0, 
            "license": "cc:by-sa/4.0", 
            "start": {
                "sense_label": "n", 
                "@id": "/c/en/ups/n", 
                "term": "/c/en/ups", 
                "language": "en", 
                "label": "ups"
            }, 
            "dataset": "/d/wiktionary/en", 
            "sources": [
                {
                    "contributor": "/s/resource/wiktionary/en", 
                    "process": "/s/process/wikiparsec/1", 
                    "@id": "/and/[/s/process/wikiparsec/1/,/s/resource/wiktionary/en/]"
                }
            ], 
            "rel": {
                "@id": "/r/FormOf", 
                "label": "FormOf"
            }, 
            "@id": "/a/[/r/FormOf/,/c/en/ups/n/,/c/en/up/]", 
            "surfaceText": null
        }, 
        {
            "end": {
                "term": "/c/en/up", 
                "@id": "/c/en/up", 
                "language": "en", 
                "label": "up"
            }, 
            "weight": 1.0, 
            "license": "cc:by-sa/4.0", 
            "start": {
                "sense_label": "v", 
                "@id": "/c/en/ups/v", 
                "term": "/c/en/ups", 
                "language": "en", 
                "label": "ups"
            }, 
            "dataset": "/d/wiktionary/en", 
            "sources": [
                {
                    "contributor": "/s/resource/wiktionary/en", 
                    "process": "/s/process/wikiparsec/1", 
                    "@id": "/and/[/s/process/wikiparsec/1/,/s/resource/wiktionary/en/]"
                }
            ], 
            "rel": {
                "@id": "/r/FormOf", 
                "label": "FormOf"
            }, 
            "@id": "/a/[/r/FormOf/,/c/en/ups/v/,/c/en/up/]", 
            "surfaceText": null
        }, 
        {
            "end": {
                "term": "/c/en/bar_tending", 
                "@id": "/c/en/bar_tending", 
                "language": "en", 
                "label": "bar tending"
            }, 
            "weight": 1.0, 
            "license": "cc:by-sa/4.0", 
            "start": {
                "sense_label": "a", 
                "@id": "/c/en/up/a", 
                "term": "/c/en/up", 
                "language": "en", 
                "label": "up"
            }, 
            "dataset": "/d/wiktionary/en", 
            "sources": [
                {
                    "contributor": "/s/resource/wiktionary/en", 
                    "process": "/s/process/wikiparsec/1", 
                    "@id": "/and/[/s/process/wikiparsec/1/,/s/resource/wiktionary/en/]"
                }
            ], 
            "rel": {
                "@id": "/r/HasContext", 
                "label": "HasContext"
            }, 
            "@id": "/a/[/r/HasContext/,/c/en/up/a/,/c/en/bar_tending/]", 
            "surfaceText": null
        }, 
        {
            "end": {
                "term": "/c/en/computing", 
                "@id": "/c/en/computing", 
                "language": "en", 
                "label": "computing"
            }, 
            "weight": 1.0, 
            "license": "cc:by-sa/4.0", 
            "start": {
                "sense_label": "a", 
                "@id": "/c/en/up/a", 
                "term": "/c/en/up", 
                "language": "en", 
                "label": "up"
            }, 
            "dataset": "/d/wiktionary/en", 
            "sources": [
                {
                    "contributor": "/s/resource/wiktionary/en", 
                    "process": "/s/process/wikiparsec/1", 
                    "@id": "/and/[/s/process/wikiparsec/1/,/s/resource/wiktionary/en/]"
                }
            ], 
            "rel": {
                "@id": "/r/HasContext", 
                "label": "HasContext"
            }, 
            "@id": "/a/[/r/HasContext/,/c/en/up/a/,/c/en/computing/]", 
            "surfaceText": null
        }, 
        {
            "end": {
                "term": "/c/en/graffiti", 
                "@id": "/c/en/graffiti", 
                "language": "en", 
                "label": "graffiti"
            }, 
            "weight": 1.0, 
            "license": "cc:by-sa/4.0", 
            "start": {
                "sense_label": "a", 
                "@id": "/c/en/up/a", 
                "term": "/c/en/up", 
                "language": "en", 
                "label": "up"
            }, 
            "dataset": "/d/wiktionary/en", 
            "sources": [
                {
                    "contributor": "/s/resource/wiktionary/en", 
                    "process": "/s/process/wikiparsec/1", 
                    "@id": "/and/[/s/process/wikiparsec/1/,/s/resource/wiktionary/en/]"
                }
            ], 
            "rel": {
                "@id": "/r/HasContext", 
                "label": "HasContext"
            }, 
            "@id": "/a/[/r/HasContext/,/c/en/up/a/,/c/en/graffiti/]", 
            "surfaceText": null
        }, 
        {
            "end": {
                "term": "/c/en/slang", 
                "@id": "/c/en/slang", 
                "language": "en", 
                "label": "slang"
            }, 
            "weight": 1.0, 
            "license": "cc:by-sa/4.0", 
            "start": {
                "sense_label": "a", 
                "@id": "/c/en/up/a", 
                "term": "/c/en/up", 
                "language": "en", 
                "label": "up"
            }, 
            "dataset": "/d/wiktionary/en", 
            "sources": [
                {
                    "contributor": "/s/resource/wiktionary/en", 
                    "process": "/s/process/wikiparsec/1", 
                    "@id": "/and/[/s/process/wikiparsec/1/,/s/resource/wiktionary/en/]"
                }
            ], 
            "rel": {
                "@id": "/r/HasContext", 
                "label": "HasContext"
            }, 
            "@id": "/a/[/r/HasContext/,/c/en/up/a/,/c/en/slang/]", 
            "surfaceText": null
        }, 
        {
            "end": {
                "term": "/c/en/india", 
                "@id": "/c/en/india", 
                "language": "en", 
                "label": "india"
            }, 
            "weight": 1.0, 
            "license": "cc:by-sa/4.0", 
            "start": {
                "sense_label": "n", 
                "@id": "/c/en/up/n", 
                "term": "/c/en/up", 
                "language": "en", 
                "label": "up"
            }, 
            "dataset": "/d/wiktionary/en", 
            "sources": [
                {
                    "contributor": "/s/resource/wiktionary/en", 
                    "process": "/s/process/wikiparsec/1", 
                    "@id": "/and/[/s/process/wikiparsec/1/,/s/resource/wiktionary/en/]"
                }
            ], 
            "rel": {
                "@id": "/r/HasContext", 
                "label": "HasContext"
            }, 
            "@id": "/a/[/r/HasContext/,/c/en/up/n/,/c/en/india/]", 
            "surfaceText": null
        }, 
        {
            "end": {
                "term": "/c/en/academia", 
                "@id": "/c/en/academia", 
                "language": "en", 
                "label": "academia"
            }, 
            "weight": 1.0, 
            "license": "cc:by-sa/4.0", 
            "start": {
                "sense_label": "r", 
                "@id": "/c/en/up/r", 
                "term": "/c/en/up", 
                "language": "en", 
                "label": "up"
            }, 
            "dataset": "/d/wiktionary/en", 
            "sources": [
                {
                    "contributor": "/s/resource/wiktionary/en", 
                    "process": "/s/process/wikiparsec/1", 
                    "@id": "/and/[/s/process/wikiparsec/1/,/s/resource/wiktionary/en/]"
                }
            ], 
            "rel": {
                "@id": "/r/HasContext", 
                "label": "HasContext"
            }, 
            "@id": "/a/[/r/HasContext/,/c/en/up/r/,/c/en/academia/]", 
            "surfaceText": null
        }
    ], 
    "@id": "/c/en/up", 
    "view": {
        "previousPage": "/c/en/up?offset=180&limit=20", 
        "paginatedProperty": "edges", 
        "@id": "/c/en/up?offset=200&limit=20", 
        "nextPage": "/c/en/up?offset=220&limit=20", 
        "firstPage": "/c/en/up?offset=0&limit=20"
    }
}